editpi/__init__.py
editpi/__main__.py
editpi/nbt_utils.py
editpi/assets/img/mcpiedit.png
editpi/assets/translations/en/LC_MESSAGES/mcpiedit.mo
editpi/assets/translations/en/LC_MESSAGES/mcpiedit.po
editpi/assets/translations/es_ES/LC_MESSAGES/mcpiedit.mo
editpi/assets/translations/es_ES/LC_MESSAGES/mcpiedit.po
editpi/assets/translations/pl/LC_MESSAGES/mcpiedit.mo
editpi/assets/translations/pl/LC_MESSAGES/mcpiedit.po
editpi/assets/translations/ru_RU/LC_MESSAGES/mcpiedit.mo
editpi/assets/translations/ru_RU/LC_MESSAGES/mcpiedit.po
editpi-1.1.dist-info/LICENSE
editpi-1.1.dist-info/LICENSE-LGPL
editpi-1.1.dist-info/METADATA
editpi-1.1.dist-info/WHEEL
editpi-1.1.dist-info/entry_points.txt
editpi-1.1.dist-info/top_level.txt
editpi-1.1.dist-info/RECORD
