Metadata-Version: 2.1
Name: editpi
Version: 1.1
Summary: A level file editor for Minecraft: Pi Edition
Home-page: https://github.com/mcpiscript
Author: mcpiscript
Author-email: mcpiscript@gmail.com
Maintainer: Alexey Pavlov
Maintainer-email: pezleha@duck.com
License: UNKNOWN
Platform: UNKNOWN
Classifier: License :: OSI Approved :: GNU Affero General Public License v3 or later (AGPLv3+)
Requires-Dist: pynbt
Provides-Extra: pyqt5
Requires-Dist: pyqt5 ; extra == 'pyqt5'
